python_awair/__init__.py
python_awair/air_data.py
python_awair/attrdict.py
python_awair/auth.py
python_awair/client.py
python_awair/const.py
python_awair/devices.py
python_awair/exceptions.py
python_awair/indices.py
python_awair/sensors.py
python_awair/user.py
python_awair-0.2.4.dist-info/LICENSE
python_awair-0.2.4.dist-info/WHEEL
python_awair-0.2.4.dist-info/METADATA
python_awair-0.2.4.dist-info/RECORD
